README.rst
setup.py
gnusocial/__init__.py
gnusocial/accounts.py
gnusocial/activity_streams.py
gnusocial/blocks.py
gnusocial/config.py
gnusocial/direct_messages.py
gnusocial/exceptions.py
gnusocial/friendships.py
gnusocial/groups.py
gnusocial/media.py
gnusocial/oauth.py
gnusocial/search.py
gnusocial/statuses.py
gnusocial/timelines.py
gnusocial/users.py
gnusocial/utils.py
gnusocial.egg-info/PKG-INFO
gnusocial.egg-info/SOURCES.txt
gnusocial.egg-info/dependency_links.txt
gnusocial.egg-info/requires.txt
gnusocial.egg-info/top_level.txt