Metadata-Version: 1.2
Name: gnusocial
Version: 4.0.0
Summary: GNU Social API for Python 3
Home-page: https://source.heropunch.io/dtluna/pygnusocial
Author: dtluna
Author-email: dtluna@openmailbox.org
License: GPLv3
Platform: any
Classifier: License :: OSI Approved :: GNU General Public License v3 (GPLv3)
Classifier: Operating System :: OS Independent
Classifier: Programming Language :: Python :: 3
Requires-Python: >=3.3
